regressionlib/__init__.py
regressionlib/exceptions/__init__.py
regressionlib/experiments/__init__.py
regressionlib/experiments/abstract_experiment.py
regressionlib/experiments/constants.py
regressionlib/experiments/forsythe_polynomial_experiment.py
regressionlib/experiments/forsythe_virtual_to_real_experiment.py
regressionlib/experiments/least_squares.py
regressionlib/experiments/multivariate_linear_regression_experiment.py
regressionlib/experiments/univariate_linear_regression_experiment.py
regressionlib/experiments/univariate_polynomial_regression_experiment.py
regressionlib/experiments/utils.py
regressionlib/experiments/matrix_utils/__init__.py
regressionlib/experiments/matrix_utils/determinant.py
regressionlib/experiments/matrix_utils/inverse.py
regressionlib/experiments/matrix_utils/multiplication.py
regressionlib/experiments/matrix_utils/transpose.py
regressionlib-0.0.3.dist-info/LICENSE
regressionlib-0.0.3.dist-info/METADATA
regressionlib-0.0.3.dist-info/WHEEL
regressionlib-0.0.3.dist-info/top_level.txt
regressionlib-0.0.3.dist-info/RECORD
