Metadata-Version: 2.1
Name: regressionlib
Version: 0.0.3
Summary: Regression library
Home-page: https://github.com/ValeryDrozd/regressionlib
Author: Valery Drozd
Author-email: drozdllera@gmail.com
License: UNKNOWN
Platform: UNKNOWN
Classifier: Programming Language :: Python :: 3
Classifier: License :: OSI Approved :: MIT License
Classifier: Operating System :: OS Independent
License-File: LICENSE
Requires-Dist: bleach (==6.0.0)
Requires-Dist: certifi (==2022.12.7)
Requires-Dist: charset-normalizer (==3.0.1)
Requires-Dist: docutils (==0.19)
Requires-Dist: idna (==3.4)
Requires-Dist: importlib-metadata (==6.0.0)
Requires-Dist: jaraco.classes (==3.2.3)
Requires-Dist: keyring (==23.13.1)
Requires-Dist: markdown-it-py (==2.1.0)
Requires-Dist: mdurl (==0.1.2)
Requires-Dist: more-itertools (==9.0.0)
Requires-Dist: mpmath (==1.2.1)
Requires-Dist: pkginfo (==1.9.6)
Requires-Dist: Pygments (==2.14.0)
Requires-Dist: readme-renderer (==37.3)
Requires-Dist: requests (==2.28.2)
Requires-Dist: requests-toolbelt (==0.10.1)
Requires-Dist: rfc3986 (==2.0.0)
Requires-Dist: rich (==13.3.1)
Requires-Dist: six (==1.16.0)
Requires-Dist: sympy (==1.11.1)
Requires-Dist: tqdm (==4.64.1)
Requires-Dist: twine (==4.0.2)
Requires-Dist: urllib3 (==1.26.14)
Requires-Dist: webencodings (==0.5.1)
Requires-Dist: zipp (==3.12.1)
